mtrust/__init__.py
mtrust/__version__.py
mtrust/core/__init__.py
mtrust/core/bias_detector.py
mtrust/core/metrics.py
mtrust/core/mitigation.py
mtrust/utils/__init__.py
mtrust/utils/visualization.py
mtrust/wrappers/__init__.py
mtrust/wrappers/base.py
mtrust/wrappers/medical.py
mtrust_medical-1.0.1.dist-info/licenses/LICENSE
tests/__init__.py
tests/test_bias_detector.py
tests/test_wrapper.py
mtrust_medical-1.0.1.dist-info/METADATA
mtrust_medical-1.0.1.dist-info/WHEEL
mtrust_medical-1.0.1.dist-info/entry_points.txt
mtrust_medical-1.0.1.dist-info/top_level.txt
mtrust_medical-1.0.1.dist-info/RECORD
