Metadata-Version: 2.4
Name: mtrust-medical
Version: 1.0.1
Summary: M-TRUST: Bias detection and mitigation for medical AI
Home-page: https://github.com/NMNayan57/mtrush_medical.git
Author: Nasim Mahmud Nayan
Author-email: smnoyan670@gmail.com
Project-URL: Bug Reports, https://github.com/NMNayan57/mtrush_medical/issues
Project-URL: Source, https://github.com/NMNayan57/mtrush_medical
Keywords: medical ai bias fairness healthcare trustworthy
Classifier: Development Status :: 4 - Beta
Classifier: Intended Audience :: Healthcare Industry
Classifier: Topic :: Scientific/Engineering :: Medical Science Apps.
Classifier: License :: OSI Approved :: MIT License
Classifier: Programming Language :: Python :: 3
Classifier: Programming Language :: Python :: 3.8
Classifier: Programming Language :: Python :: 3.9
Classifier: Programming Language :: Python :: 3.10
Requires-Python: >=3.8
License-File: LICENSE
Requires-Dist: numpy>=1.21.0
Requires-Dist: pandas>=1.3.0
Requires-Dist: torch>=1.9.0
Requires-Dist: scikit-learn>=0.24.0
Requires-Dist: Pillow>=8.0.0
Requires-Dist: tqdm>=4.62.0
Provides-Extra: dev
Requires-Dist: pytest>=7.0; extra == "dev"
Requires-Dist: black>=22.0; extra == "dev"
Requires-Dist: flake8>=4.0; extra == "dev"
Provides-Extra: viz
Requires-Dist: matplotlib>=3.5; extra == "viz"
Requires-Dist: seaborn>=0.11; extra == "viz"
Dynamic: author
Dynamic: author-email
Dynamic: classifier
Dynamic: description
Dynamic: description-content-type
Dynamic: home-page
Dynamic: keywords
Dynamic: license-file
Dynamic: project-url
Dynamic: provides-extra
Dynamic: requires-dist
Dynamic: requires-python
Dynamic: summary
